audioscope/__init__.py
audioscope/cli.py
audioscope-0.0.1.dist-info/WHEEL
audioscope-0.0.1.dist-info/entry_points.txt
audioscope-0.0.1.dist-info/METADATA
audioscope-0.0.1.dist-info/RECORD
